doglang/SemanticAnalyser.py
doglang/SymbolTable.py
doglang/SyntaxAnalyser.py
doglang/Tokenizer.py
doglang/__init__.py
doglang/cli.py
doglang/error.py
doglang/main.py
doglang-1.0.0a0.dist-info/licenses/LICENSE
doglang-1.0.0a0.dist-info/METADATA
doglang-1.0.0a0.dist-info/WHEEL
doglang-1.0.0a0.dist-info/entry_points.txt
doglang-1.0.0a0.dist-info/top_level.txt
doglang-1.0.0a0.dist-info/RECORD
